webhook2lambda2sqs/__init__.py
webhook2lambda2sqs/aws.py
webhook2lambda2sqs/config.py
webhook2lambda2sqs/func_generator.py
webhook2lambda2sqs/json_templates.py
webhook2lambda2sqs/lambda_func.py
webhook2lambda2sqs/runner.py
webhook2lambda2sqs/terraform_runner.py
webhook2lambda2sqs/tf_generator.py
webhook2lambda2sqs/utils.py
webhook2lambda2sqs/version.py
webhook2lambda2sqs/tests/__init__.py
webhook2lambda2sqs/tests/conftest.py
webhook2lambda2sqs/tests/support.py
webhook2lambda2sqs/tests/test_acceptance.py
webhook2lambda2sqs/tests/test_aws.py
webhook2lambda2sqs/tests/test_config.py
webhook2lambda2sqs/tests/test_func_generator.py
webhook2lambda2sqs/tests/test_lambda_func.py
webhook2lambda2sqs/tests/test_runner.py
webhook2lambda2sqs/tests/test_terraform_runner.py
webhook2lambda2sqs/tests/test_tf_generator.py
webhook2lambda2sqs/tests/test_utils.py
webhook2lambda2sqs/tests/test_version.py
webhook2lambda2sqs-0.2.0.dist-info/DESCRIPTION.rst
webhook2lambda2sqs-0.2.0.dist-info/METADATA
webhook2lambda2sqs-0.2.0.dist-info/RECORD
webhook2lambda2sqs-0.2.0.dist-info/WHEEL
webhook2lambda2sqs-0.2.0.dist-info/entry_points.txt
webhook2lambda2sqs-0.2.0.dist-info/metadata.json
webhook2lambda2sqs-0.2.0.dist-info/top_level.txt
