Metadata-Version: 2.0
Name: webhook2lambda2sqs
Version: 0.2.0
Summary: Generate code and manage infrastructure for receiving webhooks with AWS API Gateway and pushing to SQS via Lambda.
Home-page: https://github.com/jantman/webhook2lambda2sqs
Author: Jason Antman
Author-email: jason@jasonantman.com
License: UNKNOWN
Keywords: aws webhook lambda apigateway sqs queue amazon
Platform: UNKNOWN
Classifier: Development Status :: 3 - Alpha
Classifier: Environment :: Console
Classifier: Environment :: Other Environment
Classifier: Intended Audience :: Developers
Classifier: Intended Audience :: Information Technology
Classifier: Intended Audience :: System Administrators
Classifier: License :: OSI Approved :: GNU Affero General Public License v3 or later (AGPLv3+)
Classifier: Natural Language :: English
Classifier: Operating System :: OS Independent
Classifier: Programming Language :: Python
Classifier: Programming Language :: Python :: 2.7
Classifier: Programming Language :: Python :: 3
Classifier: Topic :: Internet :: WWW/HTTP
Classifier: Topic :: Utilities
Requires-Dist: boto3 (>=1.2.3)
Requires-Dist: requests
